ootbat2.py
ootbat2-0.1.2.data/data/OOT_LowHealth.wav
ootbat2-0.1.2.dist-info/METADATA
ootbat2-0.1.2.dist-info/WHEEL
ootbat2-0.1.2.dist-info/entry_points.txt
ootbat2-0.1.2.dist-info/top_level.txt
ootbat2-0.1.2.dist-info/RECORD
