Metadata-Version: 2.1
Name: ootbat2
Version: 0.1.2
Summary: linux low battery alerting tool
Home-page: https://github.com/vesche/ootbat2
Author: Austin Jackson
Author-email: vesche@protonmail.com
License: UNLICENSE
Classifier: Development Status :: 5 - Production/Stable
Classifier: License :: Public Domain
Classifier: Programming Language :: Python :: 3
Classifier: Programming Language :: Python :: 3.13
Requires-Dist: playsound
